Metadata-Version: 2.1
Name: aditya
Version: 0.1
Summary: My personal tools
Home-page: https://github.com/ed21b006/
Author: Aditya Raj
Author-email: adityaraj867604@gmail.com
License: MIT
Platform: UNKNOWN
Classifier: License :: OSI Approved :: MIT License
Classifier: Programming Language :: Python :: 3
Classifier: Programming Language :: Python :: 3.8
License-File: LICENSE
